setup.py
ip_address/__init__.py
ip_address/config/__init__.py
ip_address/config/ip_data.data
ip_address/config/setting.py
ip_address/ip_pack/__init__.py
ip_address/ip_pack/ip_addr.py
ip_address/ip_pack/ip_func.py
yxh_ip_address.egg-info/PKG-INFO
yxh_ip_address.egg-info/SOURCES.txt
yxh_ip_address.egg-info/dependency_links.txt
yxh_ip_address.egg-info/top_level.txt