Metadata-Version: 1.0
Name: yxh-ip-address
Version: 1.4
Summary: 可以得到ip详情ip_address地址
Home-page: UNKNOWN
Author: 易小豪
Author-email: 1764807112@qq.com
License: UNKNOWN
Platform: UNKNOWN
